chronopost_lib/__init__.py
chronopost_lib/quickcostservice.py
chronopost_lib/shippingservice.py
chronopost_lib/trackingservice.py
carrier.chronopost-2022.8.dist-info/WHEEL
carrier.chronopost-2022.8.dist-info/METADATA
carrier.chronopost-2022.8.dist-info/RECORD
